Metadata-Version: 2.1
Name: golomb-coding
Version: 1.0.6
Summary: Didactical python package implementing Golomb coding and decoding.
Home-page: https://github.com/LucaCappelletti94/golomb_coding
Author: Luca Cappelletti
Author-email: cappelletti.luca94@gmail.com
License: MIT
Platform: UNKNOWN
Classifier: Development Status :: 3 - Alpha
Classifier: License :: OSI Approved :: MIT License
Classifier: Programming Language :: Python :: 3
Provides-Extra: test
